provider_configs/product_parser_defaults.yaml
src/__init__.py
src/cli/__init__.py
src/cli/chalkbox_helpers.py
src/cli/cli.py
src/cli/commands/__init__.py
src/cli/commands/database.py
src/cli/commands/groups.py
src/cli/commands/refresh.py
src/cli/commands/track.py
src/cli/formatters.py
src/cli/helpers.py
src/cli/logging_config.py
src/cli/progress_components.py
src/config/__init__.py
src/config/config.py
src/config/config_loader.py
src/config/models.py
src/config/product_pages.py
src/config/types.py
src/database/README.md
src/database/__init__.py
src/database/converters.py
src/database/db_manager.py
src/database/models.py
src/models/__init__.py
src/models/tracked_product.py
src/price_tracker/__init__.py
src/price_tracker/bulk_tracker.py
src/price_tracker/comparator.py
src/price_tracker/group_helpers.py
src/price_tracker/group_sync.py
src/price_tracker/scraping_worker.py
src/price_tracker/tracker.py
src/providers/__init__.py
src/providers/availability_rules.py
src/providers/base_product.py
src/providers/configurable_provider.py
src/providers/field_mapper.py
src/providers/jsonld_extractor.py
src/providers/provider_factory.py
src/providers/transformations.py
src/scrapers/__init__.py
src/scrapers/async_base_provider.py
src/utils/__init__.py
src/utils/datetime_utils.py
src/utils/fuzzy_matcher.py
src/utils/product_parser.py
src/utils/retry_utils.py
src/utils/slug.py
price_scout-0.8.5b1.dist-info/LICENSE
price_scout-0.8.5b1.dist-info/METADATA
price_scout-0.8.5b1.dist-info/WHEEL
price_scout-0.8.5b1.dist-info/entry_points.txt
price_scout-0.8.5b1.dist-info/RECORD
