Metadata-Version: 2.1
Name: price-scout
Version: 0.8.5b1
Summary: Self-hosted price tracker with local data storage
Home-page: https://github.com/bulletinmybeard/price-scout
License: MIT
Keywords: price-scout,price-tracker,price-monitoring,price-comparison,web-scraping,browser-automation,e-commerce,analytics,playwright
Author: Robin Schulz
Author-email: bulletinmybeard@gmail.com
Requires-Python: >=3.12,<4.0
Classifier: Development Status :: 5 - Production/Stable
Classifier: Intended Audience :: Developers
Classifier: Intended Audience :: End Users/Desktop
Classifier: License :: OSI Approved :: MIT License
Classifier: Operating System :: OS Independent
Classifier: Programming Language :: Python :: 3
Classifier: Programming Language :: Python :: 3.12
Classifier: Topic :: Internet :: WWW/HTTP :: Dynamic Content
Classifier: Topic :: Office/Business :: Financial
Classifier: Topic :: Software Development :: Libraries :: Python Modules
Classifier: Typing :: Typed
Requires-Dist: APScheduler (>=3.11.1,<4.0.0)
Requires-Dist: PyYAML (>=6.0.1,<7.0.0)
Requires-Dist: beautifulsoup4 (>=4.12.2,<5.0.0)
Requires-Dist: chalkbox (>=2.1.1,<3.0.0)
Requires-Dist: click (>=8.1.7,<9.0.0)
Requires-Dist: croniter (>=6.0.0,<7.0.0)
Requires-Dist: duckdb (>=1.4.2,<2.0.0)
Requires-Dist: fake-useragent (>=2.2.0,<3.0.0)
Requires-Dist: httpx (>=0.28.1,<0.29.0)
Requires-Dist: lxml (>=6.0.2,<7.0.0)
Requires-Dist: mdformat-gfm (>=1.0.0,<2.0.0)
Requires-Dist: playwright (==1.56.0)
Requires-Dist: pydantic (>=2.12.4,<3.0.0)
Requires-Dist: pydantic-settings (>=2.12.0,<3.0.0)
Requires-Dist: pyld (>=2.0.4,<3.0.0)
Requires-Dist: requests (>=2.31.0,<3.0.0)
Requires-Dist: selectolax (>=0.4.0,<0.5.0)
Project-URL: Documentation, https://github.com/bulletinmybeard/price-scout#readme
Project-URL: Repository, https://github.com/bulletinmybeard/price-scout
